MANIFEST.in
README.rst
RELEASE-VERSION
setup.py
version.py
trec_dd/__init__.py
trec_dd.egg-info/PKG-INFO
trec_dd.egg-info/SOURCES.txt
trec_dd.egg-info/dependency_links.txt
trec_dd.egg-info/entry_points.txt
trec_dd.egg-info/requires.txt
trec_dd.egg-info/top_level.txt
trec_dd/harness/__init__.py
trec_dd/harness/run.py
trec_dd/harness/truth_data.py
trec_dd/harness/tests/__init__.py
trec_dd/harness/tests/test_harness.py
trec_dd/scorer/__init__.py
trec_dd/scorer/average_err.py
trec_dd/scorer/cube_test.py
trec_dd/scorer/modified_precision_at_recall.py
trec_dd/scorer/precision_at_recall.py
trec_dd/scorer/reciprocal_rank_at_recall.py
trec_dd/scorer/run.py
trec_dd/scorer/u_err.py
trec_dd/scorer/tests/__init__.py
trec_dd/system/__init__.py
trec_dd/system/ambassador_cli.py
trec_dd/system/random_system.py
trec_dd/utils/__init__.py