Metadata-Version: 1.1
Name: trec_dd
Version: 0.3.2
Summary: TREC Dynamic Domain (DD) evaluation test harness for simulating user interaction with a search engine
Home-page: http://trec-dd.org/
Author: Diffeo, Inc.
Author-email: support@diffeo.com
License: MIT/X11 license http://opensource.org/licenses/MIT
Platform: UNKNOWN
Classifier: Development Status :: 3 - Alpha
Classifier: Topic :: Utilities
Classifier: License :: OSI Approved :: MIT License
